simplebot_downloader/__init__.py
simplebot_downloader/_version.py
simplebot_downloader/util.py
simplebot_downloader-1.0.0.dist-info/LICENSE
simplebot_downloader-1.0.0.dist-info/METADATA
simplebot_downloader-1.0.0.dist-info/WHEEL
simplebot_downloader-1.0.0.dist-info/entry_points.txt
simplebot_downloader-1.0.0.dist-info/top_level.txt
simplebot_downloader-1.0.0.dist-info/RECORD
