Metadata-Version: 2.1
Name: simplebot-downloader
Version: 1.0.0
Summary: File downloader plugin for SimpleBot
Home-page: https://github.com/adbenitez/simplebot_downloader
Author: adbenitez
Author-email: adbenitez@nauta.cu
License: MPL
Keywords: simplebot plugin deltachat
Platform: UNKNOWN
Classifier: Development Status :: 3 - Alpha
Classifier: Environment :: Plugins
Classifier: Programming Language :: Python :: 3
Classifier: License :: OSI Approved :: Mozilla Public License 2.0 (MPL 2.0)
Classifier: Operating System :: OS Independent
Classifier: Topic :: Utilities
License-File: LICENSE
Requires-Dist: simplebot (>=2.4.0)
Requires-Dist: requests (>=2.27.1)
Requires-Dist: multivolumefile (>=0.2.3)
Requires-Dist: py7zr (>=0.18.5)
Provides-Extra: dev
Requires-Dist: simplebot (>=2.4.0) ; extra == 'dev'
Requires-Dist: requests (>=2.27.1) ; extra == 'dev'
Requires-Dist: multivolumefile (>=0.2.3) ; extra == 'dev'
Requires-Dist: py7zr (>=0.18.5) ; extra == 'dev'
Requires-Dist: pytest (>=7.1.2) ; extra == 'dev'
Requires-Dist: requests-mock (>=1.9.3) ; extra == 'dev'
Requires-Dist: black (>=22.3.0) ; extra == 'dev'
Requires-Dist: mypy (>=0.942) ; extra == 'dev'
Requires-Dist: isort (>=5.10.1) ; extra == 'dev'
Requires-Dist: pylint (>=2.13.7) ; extra == 'dev'
Requires-Dist: pylama (>=8.3.8) ; extra == 'dev'
Requires-Dist: types-requests (>=2.27.20) ; extra == 'dev'
Provides-Extra: test
Requires-Dist: pytest (>=7.1.2) ; extra == 'test'
Requires-Dist: requests-mock (>=1.9.3) ; extra == 'test'
